{
  "zig_zag_center":
  [
    {"x":350, "y":100, "action":"none"},
    {"x":450, "y":200, "action":"none"},
    {"x":350, "y":300, "action":"none"},
    {"x":450, "y":400, "action":"none"},
    {"x":350, "y":500, "action":"none"},
    {"x":450, "y":600, "action":"none"},
  ],
  "zig_zag_left":
  [
    {"x":50, "y":100, "action":"none"},
    {"x":150, "y":200, "action":"none"},
    {"x":50, "y":300, "action":"none"},
    {"x":150, "y":400, "action":"none"},
    {"x":50, "y":500, "action":"none"},
    {"x":150, "y":600, "action":"none"},
  ],
  "zig_zag_right":
  [
    {"x":750, "y":100, "action":"none"},
    {"x":650, "y":200, "action":"none"},
    {"x":750, "y":300, "action":"none"},
    {"x":650, "y":400, "action":"none"},
    {"x":750, "y":500, "action":"none"},
    {"x":650, "y":600, "action":"none"},
  ],
  "go_foward_center_and_shoot":
  [
    {"x":400, "y":100, "action":"shoot"},
    {"x":400, "y":150, "action":"none"},
    {"x":400, "y":200, "action":"shoot"},
    {"x":400, "y":250, "action":"none"},
    {"x":400, "y":300, "action":"shoot"},
    {"x":400, "y":350, "action":"none"},
    {"x":400, "y":400, "action":"shoot"},
    {"x":400, "y":450, "action":"none"},
    {"x":400, "y":500, "action":"shoot"},
    {"x":400, "y":550, "action":"none"},
  ],
  "go_foward_left_and_shoot":
  [
    {"x":200, "y":100, "action":"shoot"},
    {"x":200, "y":150, "action":"none"},
    {"x":200, "y":200, "action":"shoot"},
    {"x":200, "y":150, "action":"none"},
    {"x":200, "y":200, "action":"shoot"},
    {"x":200, "y":250, "action":"none"},
    {"x":200, "y":300, "action":"shoot"},
    {"x":200, "y":350, "action":"none"},
    {"x":200, "y":400, "action":"shoot"},
    {"x":200, "y":450, "action":"none"},
    {"x":200, "y":500, "action":"shoot"},
    {"x":200, "y":550, "action":"none"},
  ],
  "go_foward_right_and_shoot":
  [
    {"x":600, "y":100, "action":"shoot"},
    {"x":600, "y":150, "action":"none"},
    {"x":600, "y":200, "action":"shoot"},
    {"x":600, "y":150, "action":"none"},
    {"x":600, "y":200, "action":"shoot"},
    {"x":600, "y":250, "action":"none"},
    {"x":600, "y":300, "action":"shoot"},
    {"x":600, "y":350, "action":"none"},
    {"x":600, "y":400, "action":"shoot"},
    {"x":600, "y":450, "action":"none"},
    {"x":600, "y":500, "action":"shoot"},
    {"x":600, "y":550, "action":"none"},
  ],
  "top_wall":
  [
    {"x":50, "y":100, "action":"none"},
    {"x":750, "y":100, "action":"repeat"},
  ],

  "shoot_by_top":
  [
    {"x":50, "y":50, "action":"shoot"},
    {"x":150, "y":50, "action":"shoot"},
    {"x":250, "y":50, "action":"shoot"},
    {"x":350, "y":50, "action":"shoot"},
    {"x":450, "y":50, "action":"shoot"},
    {"x":550, "y":50, "action":"shoot"},
    {"x":650, "y":50, "action":"shoot"},
    {"x":750, "y":50, "action":"shoot"},
    {"x":650, "y":50, "action":"shoot"},
    {"x":550, "y":50, "action":"shoot"},
    {"x":450, "y":50, "action":"shoot"},
    {"x":350, "y":50, "action":"shoot"},
    {"x":250, "y":50, "action":"shoot"},
    {"x":150, "y":50, "action":"shoot"},
    {"x":50, "y":50, "action":"repeat"},
  ],
  "drop_by_50": [ {"x":50, "y":50, "action":"none"} ],
  "drop_by_150": [ {"x":150, "y":50, "action":"none"} ],
  "drop_by_250": [ {"x":250, "y":50, "action":"none"} ],
  "drop_by_350": [ {"x":350, "y":50, "action":"none"} ],
  "drop_by_450": [ {"x":450, "y":50, "action":"none"} ],
  "drop_by_550": [ {"x":550, "y":50, "action":"none"} ],
  "drop_by_650": [ {"x":650, "y":50, "action":"none"} ],
  "drop_by_750": [ {"x":750, "y":50, "action":"none"} ],
  "boss_01":
  [
    {"x":200, "y":100, "action":"shoot"},
    {"x":250, "y":100, "action":"shoot"},
    {"x":300, "y":100, "action":"shoot"},
    {"x":350, "y":100, "action":"shoot"},
    {"x":400, "y":100, "action":"shoot"},
    {"x":450, "y":100, "action":"shoot"},
    {"x":500, "y":100, "action":"shoot"},
    {"x":550, "y":100, "action":"shoot"},
    {"x":600, "y":100, "action":"shoot"},
    {"x":550, "y":100, "action":"shoot"},
    {"x":500, "y":100, "action":"shoot"},
    {"x":450, "y":100, "action":"shoot"},
    {"x":400, "y":100, "action":"shoot"},
    {"x":350, "y":100, "action":"shoot"},
    {"x":300, "y":100, "action":"shoot"},
    {"x":250, "y":100, "action":"shoot"},
    {"x":200, "y":100, "action":"repeat"},
  ],
  "boss_02":
  [
    {"x":200, "y":200, "action":"shoot"},
    {"x":200, "y":250, "action":"shoot"},
    {"x":200, "y":300, "action":"shoot"},
    {"x":200, "y":350, "action":"shoot"},
    {"x":200, "y":400, "action":"shoot"},
    {"x":250, "y":400, "action":"shoot"},
    {"x":300, "y":400, "action":"shoot"},
    {"x":350, "y":400, "action":"shoot"},
    {"x":400, "y":400, "action":"shoot"},
    {"x":450, "y":400, "action":"shoot"},
    {"x":500, "y":400, "action":"shoot"},
    {"x":550, "y":400, "action":"shoot"},
    {"x":600, "y":400, "action":"shoot"},
    {"x":600, "y":350, "action":"shoot"},
    {"x":600, "y":300, "action":"shoot"},
    {"x":600, "y":250, "action":"shoot"},
    {"x":600, "y":200, "action":"shoot"},
    {"x":550, "y":200, "action":"shoot"},
    {"x":500, "y":200, "action":"shoot"},
    {"x":450, "y":200, "action":"shoot"},
    {"x":400, "y":200, "action":"shoot"},
    {"x":350, "y":200, "action":"shoot"},
    {"x":300, "y":200, "action":"shoot"},
    {"x":250, "y":200, "action":"shoot"},
    {"x":200, "y":200, "action":"repeat"},
  ]
}